{
    "16430s": {
        "submission": "0",
        "time": 1643,
        "score": 0,
        "extra": [
            "0"
        ]
    },
    "18751s": {
        "submission": "1",
        "time": 1875,
        "score": 0,
        "extra": []
    },
    "30562s": {
        "submission": "2",
        "time": 3056,
        "score": 32.0,
        "extra": [
            "32",
            "0"
        ]
    },
    "31243s": {
        "submission": "3",
        "time": 3124,
        "score": 0.0,
        "extra": [
            "0",
            "0"
        ]
    }
}